AUTHORS
LICENSE
MANIFEST.in
README.rst
setup.cfg
setup.py
django_grappelli_latest.egg-info/PKG-INFO
django_grappelli_latest.egg-info/SOURCES.txt
django_grappelli_latest.egg-info/dependency_links.txt
django_grappelli_latest.egg-info/not-zip-safe
django_grappelli_latest.egg-info/top_level.txt
docs/bestpractice.rst
docs/changelog.rst
docs/conf.py
docs/contributing.rst
docs/customization.rst
docs/dashboard_api.rst
docs/dashboard_setup.rst
docs/djangoissues.rst
docs/faq.rst
docs/help.rst
docs/index.rst
docs/internals.rst
docs/javascripts.rst
docs/quickstart.rst
docs/releasenotes.rst
docs/templates.rst
docs/thirdparty.rst
docs/troubleshooting.rst
grappelli/__init__.py
grappelli/forms.py
grappelli/models.py
grappelli/settings.py
grappelli/urls.py
grappelli/dashboard/__init__.py
grappelli/dashboard/apps.py
grappelli/dashboard/dashboards.py
grappelli/dashboard/modules.py
grappelli/dashboard/registry.py
grappelli/dashboard/utils.py
grappelli/dashboard/management/__init__.py
grappelli/dashboard/management/commands/__init__.py
grappelli/dashboard/management/commands/customdashboard.py
grappelli/dashboard/templates/admin/index.html
grappelli/dashboard/templates/grappelli/dashboard/dashboard.html
grappelli/dashboard/templates/grappelli/dashboard/dashboard.txt
grappelli/dashboard/templates/grappelli/dashboard/dummy.html
grappelli/dashboard/templates/grappelli/dashboard/module.html
grappelli/dashboard/templates/grappelli/dashboard/modules/app_list.html
grappelli/dashboard/templates/grappelli/dashboard/modules/feed.html
grappelli/dashboard/templates/grappelli/dashboard/modules/group.html
grappelli/dashboard/templates/grappelli/dashboard/modules/link_list.html
grappelli/dashboard/templates/grappelli/dashboard/modules/model_list.html
grappelli/dashboard/templates/grappelli/dashboard/modules/recent_actions.html
grappelli/dashboard/templatetags/__init__.py
grappelli/dashboard/templatetags/grp_dashboard_tags.py
grappelli/static/admin/js/LICENSE-JQUERY.txt
grappelli/static/admin/js/SelectBox.js
grappelli/static/admin/js/SelectFilter2.js
grappelli/static/admin/js/actions.js
grappelli/static/admin/js/actions.min.js
grappelli/static/admin/js/calendar.js
grappelli/static/admin/js/collapse.js
