Metadata-Version: 1.1
Name: django-grappelli-latest
Version: 2.8.1a
Summary: A jazzy skin for the Django Admin-Interface.
Home-page: http://django-grappelli.readthedocs.org
Author: Patrick Kranzlmueller, Axel Swoboda (vonautomatisch)
Author-email: office@vonautomatisch.at
License: BSD
Platform: UNKNOWN
Classifier: Development Status :: 5 - Production/Stable
Classifier: Environment :: Web Environment
Classifier: Framework :: Django
Classifier: Intended Audience :: Developers
Classifier: License :: OSI Approved :: BSD License
Classifier: Operating System :: OS Independent
Classifier: Programming Language :: Python
Classifier: Programming Language :: Python :: 2
Classifier: Programming Language :: Python :: 2.6
Classifier: Programming Language :: Python :: 2.7
Classifier: Programming Language :: Python :: 3
Classifier: Programming Language :: Python :: 3.1
Classifier: Programming Language :: Python :: 3.2
Classifier: Programming Language :: Python :: 3.3
